{"lts": 1355153458034, "htotal": 2, "code": "ID", "siw": 0, "dh": 0, "hiw": 2, "rh": 2, "evotes": 4, "ih": 0, "si": 0, "state": "Idaho", "races": {"I": [], "P": [{"raceid": "IDP00", "ip": "D", "ncon": false, "wparty": "R", "xpoll": false, "wname": "Romney", "ts": 1355153458034, "keyrace": false, "state": "Idaho", "bgs": false, "candidates": [{"votes": 420911, "winner": true, "suffix": "", "mname": "", "usesuffix": false, "vpct": 64, "lname": "Romney", "evotes": 4, "fname": "Mitt", "party": "R", "cvotes": "420,911", "id": 893, "inc": false}, {"votes": 212787, "winner": false, "suffix": "", "mname": "", "usesuffix": false, "vpct": 33, "lname": "Obama", "evotes": 0, "fname": "Barack", "party": "D", "cvotes": "212,787", "id": 1918, "inc": true}], "cmap": true, "pctsrep": 100, "electiondate": "20121106", "status": "called", "title2": "", "cresults": true, "rtype": "P", "polls": [], "sw": false, "pollclose": 1352260800000, "race": "President"}], "S": [], "G": [], "H": [{"raceid": "IDH01", "ip": "R", "ncon": false, "wparty": "R", "xpoll": false, "wname": "Labrador", "ts": 1352385168000, "keyrace": false, "state": "Idaho", "bgs": false, "candidates": [{"votes": 199445, "winner": true, "suffix": "", "mname": "", "usesuffix": false, "vpct": 63, "lname": "Labrador", "fname": "Raul", "party": "R", "cvotes": "199,445", "id": 60527, "inc": true}, {"votes": 97403, "winner": false, "suffix": "", "mname": "", "usesuffix": false, "vpct": 31, "lname": "Farris", "fname": "Jimmy", "party": "D", "cvotes": "97,403", "id": 61783, "inc": false}], "cmap": true, "pctsrep": 100, "electiondate": "20121106", "status": "called", "title2": "", "cresults": true, "rtype": "H", "polls": [], "sw": false, "pollclose": 1352260800000, "race": "House 01"}, {"raceid": "IDH02", "ip": "R", "ncon": false, "wparty": "R", "xpoll": false, "wname": "Simpson", "ts": 1352385168000, "keyrace": false, "state": "Idaho", "bgs": false, "candidates": [{"votes": 207244, "winner": true, "suffix": "", "mname": "", "usesuffix": false, "vpct": 65, "lname": "Simpson", "fname": "Mike", "party": "R", "cvotes": "207,244", "id": 504, "inc": true}, {"votes": 110817, "winner": false, "suffix": "", "mname": "", "usesuffix": false, "vpct": 35, "lname": "LeFavour", "fname": "Nicole", "party": "D", "cvotes": "110,817", "id": 61784, "inc": false}], "cmap": true, "pctsrep": 100, "electiondate": "20121106", "status": "called", "title2": "", "cresults": true, "rtype": "H", "polls": [], "sw": false, "pollclose": 1352260800000, "race": "House 02"}]}, "giw": 0, "bgs": false, "hi": 2, "gil": 0, "hil": 0, "hch": "", "gi": 0, "sil": 0}